Metadata-Version: 1.0
Name: zmg
Version: 0.1
Summary: zmg desc
Home-page: https://github.com/jackgithup/FileLibrary
Author: jack
Author-email: 18513102876@163.com
License: MIT
Platform: UNKNOWN
